bl_scrypture/__init__.py
bl_scrypture/application/__init__.py
bl_scrypture/application/use_cases/__init__.py
bl_scrypture/application/use_cases/add_events.py
bl_scrypture/configuration/__init__.py
bl_scrypture/configuration/cli.py
bl_scrypture/configuration/wsgi.py
bl_scrypture/domain/__init__.py
bl_scrypture/infrastructure/__init__.py
bl_scrypture/infrastructure/click.py
bl_scrypture/infrastructure/flask/__init__.py
bl_scrypture/infrastructure/flask/services.py
bl_scrypture/infrastructure/flask/streams.py
bl_scrypture/infrastructure/redis.py
bl_scrypture/infrastructure/settings.py
bl_scrypture/interface/__init__.py
bl_scrypture/interface/controllers.py
bl_scrypture/interface/presenters.py
bl_scrypture-0.1.0a2.dist-info/METADATA
bl_scrypture-0.1.0a2.dist-info/WHEEL
bl_scrypture-0.1.0a2.dist-info/entry_points.txt
bl_scrypture-0.1.0a2.dist-info/RECORD
