Metadata-Version: 2.1
Name: bl_scrypture
Version: 0.1.0a2
Summary: An event store.
License: AGPL-3.0-or-later
Author: Tanguy Le Carrour
Author-email: tanguy@bioneland.org
Requires-Python: >=3.9,<4.0
Classifier: License :: OSI Approved :: GNU Affero General Public License v3 or later (AGPLv3+)
Classifier: Programming Language :: Python :: 3
Classifier: Programming Language :: Python :: 3.9
Classifier: Programming Language :: Python :: 3.10
Classifier: Programming Language :: Python :: 3.11
Classifier: Programming Language :: Python :: 3.12
Requires-Dist: Flask (>=3.0.0,<4.0.0)
Requires-Dist: bl-seth (>=0.2.0,<0.3.0)
Requires-Dist: bles (>=1.0.0a1,<2.0.0)
Requires-Dist: blessql (>=1.0.0a0,<2.0.0)
Requires-Dist: click (>=8.1.3,<9.0.0)
Requires-Dist: redis (>=4.6.0,<5.0.0)
Requires-Dist: sqlalchemy (>=2.0.23,<3.0.0)
